mkedit/__init__.py
mkedit/core/DataClass.py
mkedit/core/Dialog.py
mkedit/core/EditCenter.py
mkedit/core/FileUtils.py
mkedit/core/ImageUpload.py
mkedit/core/MkEdit.py
mkedit/core/MkUtuls.py
mkedit/core/__init__.py
mkedit/core/dialog/ComboBoxDialog.py
mkedit/core/dialog/LoadingHitDialog.py
mkedit/core/dialog/PrewViewDialog.py
mkedit/core/dialog/SearchHitDialog.py
mkedit/core/dialog/__init__.py
mkedit/core/widgets/EditView.py
mkedit/core/widgets/HtmlTemplates.py
mkedit/core/widgets/LineNumberArea.py
mkedit/core/widgets/PreView.py
mkedit/core/widgets/ToolBarButton.py
mkedit/core/widgets/__init__.py
MkEdit-1.1.6.dist-info/LICENSE
MkEdit-1.1.6.dist-info/METADATA
MkEdit-1.1.6.dist-info/WHEEL
MkEdit-1.1.6.dist-info/top_level.txt
MkEdit-1.1.6.dist-info/RECORD
