Metadata-Version: 2.1
Name: MkEdit
Version: 1.1.6
Summary: 基于Pyside2 实现的markdwon edit
Home-page: https://gitee.com/osczaizai/PySide2MkEdit.git
Author: Anjie Guan
Author-email: angelswy163@163.com
License: MIT
Platform: UNKNOWN
Classifier: License :: OSI Approved :: MIT License
Classifier: Programming Language :: Python
Classifier: Programming Language :: Python :: 3
Classifier: Programming Language :: Python :: 3.6
Classifier: Programming Language :: Python :: Implementation :: CPython
Classifier: Programming Language :: Python :: Implementation :: PyPy
Requires-Python: >=3.6.0
Requires-Dist: rx (>=3.0.1)
Requires-Dist: PySide2 (>=5.13.2)
Requires-Dist: mistune (>=0.8.4)
Requires-Dist: rxbus (>=0.1.2)
Requires-Dist: qtawesome (>=0.6.0)
Requires-Dist: PySild2QtScheduler (>=0.0.3)
Requires-Dist: EasyMenusBar (>=0.3.3)
